psdm_qs_cli/QSGenerateExcelSpreadSheet.py
psdm_qs_cli/QSGenerateJSON.py
psdm_qs_cli/QuestionnaireClient.py
psdm_qs_cli/__init__.py
psdm_qs_cli/_version.py
psdm_qs_cli/version.py
psdm_qs_cli-0.3.8.dist-info/AUTHORS.rst
psdm_qs_cli-0.3.8.dist-info/LICENSE
psdm_qs_cli-0.3.8.dist-info/METADATA
psdm_qs_cli-0.3.8.dist-info/WHEEL
psdm_qs_cli-0.3.8.dist-info/entry_points.txt
psdm_qs_cli-0.3.8.dist-info/top_level.txt
psdm_qs_cli-0.3.8.dist-info/RECORD
