Metadata-Version: 2.1
Name: psdm_qs_cli
Version: 0.3.8
Summary: Python client for interacting with the PCDS questionnaire.
Author: SLAC National Accelerator Laboratory
License: Copyright (c) 2023, The Board of Trustees of the Leland Stanford Junior
Classifier: Development Status :: 2 - Pre-Alpha
Classifier: Natural Language :: English
Classifier: Programming Language :: Python :: 3
Requires-Python: >=3.9
License-File: LICENSE
License-File: AUTHORS.rst
Requires-Dist: lcls-krtc
Requires-Dist: requests
Requires-Dist: openpyxl
Provides-Extra: doc
Requires-Dist: sphinx ; extra == 'doc'
Requires-Dist: sphinx-rtd-theme ; extra == 'doc'
Requires-Dist: sphinxcontrib-jquery ; extra == 'doc'
Provides-Extra: test
Requires-Dist: pytest ; extra == 'test'
